discord/ext/slash/__init__.py
discord_ext_slash-0.9.2.dist-info/LICENSE.txt
discord_ext_slash-0.9.2.dist-info/METADATA
discord_ext_slash-0.9.2.dist-info/WHEEL
discord_ext_slash-0.9.2.dist-info/top_level.txt
discord_ext_slash-0.9.2.dist-info/RECORD
