Metadata-Version: 2.1
Name: discord-ext-slash
Version: 0.9.2
Summary: Support slash commands with discord.py.
Home-page: https://github.com/Kenny2github/discord-ext-slash
Author: kenny2discord
Author-email: kenny2minecraft@gmail.com
License: MIT
Keywords: discord slash commands
Platform: UNKNOWN
Classifier: Development Status :: 3 - Alpha
Classifier: Intended Audience :: Developers
Classifier: Topic :: Communications :: Chat
Classifier: License :: OSI Approved :: MIT License
Classifier: Programming Language :: Python :: 3 :: Only
Classifier: Programming Language :: Python :: 3.7
Requires-Python: >=3.7
Requires-Dist: discord.py (<1.8,>=1.5)
